.bzrignore
COPYING.txt
README.txt
TODO.txt
ez_setup.py
replybot.cfg.sample
setup.cfg
setup.py
botlib/__init__.py
botlib/botlog.py
botlib/configuration.py
botlib/database.py
botlib/i18n.py
botlib/main.py
botlib/options.py
botlib/reply.py
botlib/replybot.sql
botlib/version.py
botlib/docs/__init__.py
botlib/docs/configuration.txt
botlib/docs/database.txt
botlib/docs/reply.txt
botlib/docs/schema.txt
botlib/testing/__init__.py
botlib/testing/smtpctl.py
botlib/testing/smtpsrv.py
botlib/testing/test_01.cfg
botlib/testing/test_02.cfg
botlib/testing/test_03.cfg
docs/replybot.tex
replybot.egg-info/PKG-INFO
replybot.egg-info/SOURCES.txt
replybot.egg-info/dependency_links.txt
replybot.egg-info/entry_points.txt
replybot.egg-info/requires.txt
replybot.egg-info/top_level.txt