Metadata-Version: 1.0
Name: replybot
Version: 5.0.0a4
Summary: The Python Replybot
Home-page: http://launchpad.net/replybot
Author: Barry Warsaw
Author-email: barry@python.org
License: GPLv3
Keywords: email
Platform: UNKNOWN
